README.md
setup.py
postprice/__init__.py
postprice/postprice.py
postprice.egg-info/PKG-INFO
postprice.egg-info/SOURCES.txt
postprice.egg-info/dependency_links.txt
postprice.egg-info/requires.txt
postprice.egg-info/top_level.txt