Metadata-Version: 2.1
Name: postprice
Version: 1.0.0
Summary: Calculates Russian Post delivery costs
Home-page: https://github.com/egorgvo/postprice
Author: Egor Gvo
Author-email: work.egvo@ya.ru
License: MIT
Platform: UNKNOWN
Classifier: License :: OSI Approved :: MIT License
Classifier: Programming Language :: Python :: 3
